unfazed_mcp/__init__.py
unfazed_mcp/backends/__init__.py
unfazed_mcp/backends/mcp.py
unfazed_mcp-0.0.1.dist-info/METADATA
unfazed_mcp-0.0.1.dist-info/WHEEL
unfazed_mcp-0.0.1.dist-info/licenses/LICENSE
unfazed_mcp-0.0.1.dist-info/RECORD
