Metadata-Version: 2.4
Name: unfazed-mcp
Version: 0.0.1
Summary: Model Context Protocol for Unfazed
License-File: LICENSE
Requires-Python: >=3.12
Requires-Dist: fastmcp>=2.10.6
Requires-Dist: pydantic>=2.10.6
Requires-Dist: unfazed>=0.0.13
